<annotation verified="yes">
	<folder>JPEGImages</folder>
	<filename>NImage39.jpg</filename>
	<path>/Users/nickjean-baptiste/Desktop/things/JPEGImages/NImage39.jpg</path>
	<source>
		<database>Unknown</database>
	</source>
	<size>
		<width>3036</width>
		<height>4048</height>
		<depth>3</depth>
	</size>
	<segmented>0</segmented>
	<object>
		<name>o</name>
		<pose>Unspecified</pose>
		<truncated>0</truncated>
		<difficult>0</difficult>
		<bndbox>
			<xmin>1234</xmin>
			<ymin>1695</ymin>
			<xmax>1621</xmax>
			<ymax>2220</ymax>
		</bndbox>
	</object>
</annotation>
